lichs/Game.py
lichs/__main__.py
lichs/api_key.py
lichs/tempCodeRunnerFile.py
lichs-1.3.1.dist-info/LICENSE
lichs-1.3.1.dist-info/METADATA
lichs-1.3.1.dist-info/WHEEL
lichs-1.3.1.dist-info/entry_points.txt
lichs-1.3.1.dist-info/top_level.txt
lichs-1.3.1.dist-info/RECORD
