Metadata-Version: 2.1
Name: lichs
Version: 1.3.1
Summary: Play chess against other real players in your terminal using Lichess
Home-page: https://github.com/Cqsi/lichs
Author: Casimir Rönnlöf
Author-email: casimirr04@gmail.com
License: UNKNOWN
Platform: UNKNOWN
Classifier: Programming Language :: Python :: 3
Classifier: License :: OSI Approved :: MIT License
Requires-Python: >=3.6
Requires-Dist: python-chess
Requires-Dist: berserk
